<?xml version="1.0" encoding="UTF-8"?>
<!DOCTYPE TrackElements>

<ScenarioXML>

    <NewLightingXML>true</NewLightingXML>
    <SunPositionXML>45,180,0</SunPositionXML> <!-- x: 0 = i horisonten 90 = midt oppå himmelen y: rotasjon 0-360 0=nord 90=øst 180=sør 270=vest z: ikke i bruk -->
    <AmbientLightXML>0.2</AmbientLightXML> <!-- 0 til 255 -->

  <!--   
  -->
	<SectionXML>
		<NameXML>nitkatman1</NameXML>
	</SectionXML>
     
  <SectionXML>
          <NameXML>storehammer0</NameXML>
  </SectionXML>

	<SectionXML>
		<NameXML>storehammer1</NameXML>
                <EndPointNextStartPointIndexXML>0</EndPointNextStartPointIndexXML>
	</SectionXML>
    
	<SectionXML>
		<NameXML>revestua1</NameXML>
                <EndPointNextStartPointIndexXML>0</EndPointNextStartPointIndexXML>
	</SectionXML>
 

	<SectionXML>
		<NameXML>hakafjell1</NameXML>
                <EndPointNextStartPointIndexXML>0</EndPointNextStartPointIndexXML>
	</SectionXML>
      
	<SectionXML>
		<NameXML>GRS</NameXML>
               <EndPointNextStartPointIndexXML>3</EndPointNextStartPointIndexXML> 
	</SectionXML>
 
	<SectionXML>
		<NameXML>UFJS1</NameXML>
	</SectionXML>
     <!--           
	<SectionXML>
		<NameXML>UFJS2</NameXML>
	</SectionXML>
 
    -->

    <TogXML>
        <IdXML>100</IdXML>
        <ModelXML>togsett</ModelXML>
        <StartSeksjonXML>nitkatman1</StartSeksjonXML>
        <StartposXML>1680</StartposXML>
        <StartposSideveisXML>0</StartposSideveisXML>
        <StartModusXML>104</StartModusXML>        
        <InfoXML></InfoXML> 
    </TogXML>             
	
    <StartTimeXML>14:00</StartTimeXML> <!-- STARTTIDSPUNKT FOR SCENARIET -->
    
    <TogNrXML>319</TogNrXML>
    
    <PersonStartPosisjonXML>forerrom2_sittende</PersonStartPosisjonXML>
    
    <SlideMappeXML>infoslides_scenario/100</SlideMappeXML>
    <SlideOffsetInfoXML>70</SlideOffsetInfoXML>
    <SlideOffsetOppgaverXML>80</SlideOffsetOppgaverXML>
    <NettbrettFilXML>nettbrettslides_scenario/tog 319.png</NettbrettFilXML>         
	
    <!-- NITTEBERG -->
    <ScenarioEventXML>
        <ScenarioActionStateChangerXML>
            <IdXML>pos:1753_sec:nitkatman1_type:hs3</IdXML>
            <StateXML>22</StateXML>
        </ScenarioActionStateChangerXML>
    </ScenarioEventXML>	
  
    <ScenarioEventXML>
        <ScenarioTriggerTimeXML>						
            <SecondsXML>2</SecondsXML>		
        </ScenarioTriggerTimeXML>			
	
        <ScenarioActionFreezeXML>						
            <MessageXML>freeze_nifty:niftyinfo1 imagefil=Lysbilde1.PNG
            </MessageXML>
        </ScenarioActionFreezeXML>
    </ScenarioEventXML>
    
	
    <!-- KATTDORP -->
    <!-- frys 1 okt hast-->
    <ScenarioEventXML>
        <ScenarioTriggerTrackPosXML>		
            <IdXML>100</IdXML>							
            <SectionNameXML>nitkatman1</SectionNameXML>	
            <StartVertexXML>0,0,2735</StartVertexXML>
        </ScenarioTriggerTrackPosXML>
    
        <ScenarioActionFreezeXML>						
            <MessageXML>freeze_nifty:niftyinfo1 imagefil=Lysbilde2.PNG oppg1=true oppg2=false
            </MessageXML>
        </ScenarioActionFreezeXML>	  	
    </ScenarioEventXML>
  
    <!-- frys 2 okt avvik hast-->
    <ScenarioEventXML>
        <ScenarioTriggerTrackPosXML>		
            <IdXML>100</IdXML>							
            <SectionNameXML>nitkatman1</SectionNameXML>	
            <StartVertexXML>0,0,3315</StartVertexXML>
        </ScenarioTriggerTrackPosXML>
    
        <ScenarioActionFreezeXML>						
            <MessageXML>freeze_nifty:niftyinfo1 imagefil=Lysbilde3.PNG oppg1=true oppg2=false oppg3=true
            </MessageXML>
        </ScenarioActionFreezeXML>	  	
    </ScenarioEventXML>

    <!-- frys 3 okt avvik hast ut-->
    <ScenarioEventXML>
        <ScenarioTriggerTrackPosXML>		
            <IdXML>100</IdXML>							
            <SectionNameXML>nitkatman1</SectionNameXML>	
            <StartVertexXML>5,0,4745</StartVertexXML>
        </ScenarioTriggerTrackPosXML>
    
        <ScenarioActionFreezeXML>						
            <MessageXML>freeze_nifty:niftyinfo1 imagefil=Lysbilde4.PNG oppg1=true oppg2=true
            </MessageXML>
        </ScenarioActionFreezeXML>	  	
    </ScenarioEventXML>  
      
    <ScenarioEventXML>
        <ScenarioActionStateChangerXML>
            <IdXML>pos:4130_sec:nitkatman1_type:hs3</IdXML>
            <StateXML>21</StateXML>
        </ScenarioActionStateChangerXML>
    
        <ScenarioActionStateChangerXML>
            <IdXML>pos:4330_sec:nitkatman1</IdXML>
            <StateXML>1</StateXML>
        </ScenarioActionStateChangerXML>
		
        <ScenarioActionStateChangerXML>
            <IdXML>pos:4830_sec:nitkatman1_type:sw</IdXML>
            <StateXML>1</StateXML>
        </ScenarioActionStateChangerXML>
		
        <ScenarioActionStateChangerXML>
            <IdXML>pos:4758_sec:nitkatman1_type:hs2</IdXML>
            <StateXML>21</StateXML>
        </ScenarioActionStateChangerXML>
    </ScenarioEventXML>

    <!-- VESTLI BP-->
    <ScenarioEventXML>
        <ScenarioActionStateChangerXML>
            <IdXML>pos:7240_sec:nitkatman1_type:hs3</IdXML>
            <StateXML>22</StateXML>
        </ScenarioActionStateChangerXML>
    </ScenarioEventXML>	
	
    <!-- Frys hast ned-->
    <ScenarioEventXML>
        <ScenarioTriggerTrackPosXML>		
            <IdXML>100</IdXML>							
            <SectionNameXML>nitkatman1</SectionNameXML>	
            <StartVertexXML>0,0,8037</StartVertexXML>
        </ScenarioTriggerTrackPosXML>		
    
        <ScenarioActionFreezeXML>						
            <MessageXML>freeze_nifty:niftyinfo1 imagefil=Lysbilde5.PNG oppg1=false oppg2=true oppg3=true oppg4=false
            </MessageXML>
        </ScenarioActionFreezeXML>
    </ScenarioEventXML>
  
    <!-- Frys mark merke-->
    <ScenarioEventXML>
        <ScenarioTriggerTrackPosXML>		
            <IdXML>100</IdXML>							
            <SectionNameXML>nitkatman1</SectionNameXML>	
            <StartVertexXML>0,0,8537</StartVertexXML>
        </ScenarioTriggerTrackPosXML>		
    
        <ScenarioActionFreezeXML>						
            <MessageXML>freeze_nifty:niftyinfo1 imagefil=Lysbilde6.PNG oppg1=false oppg2=true oppg3=true
            </MessageXML>
        </ScenarioActionFreezeXML>
    </ScenarioEventXML>

    <!-- MANGEBERG-->
    <!-- innkj utkj avvik-->
    <ScenarioEventXML>
        <ScenarioActionStateChangerXML>
            <IdXML>pos:9490_sec:nitkatman1_type:hs3</IdXML>
            <StateXML>21</StateXML>
        </ScenarioActionStateChangerXML>
    
        <ScenarioActionStateChangerXML>
            <IdXML>pos:9690_sec:nitkatman1</IdXML>
            <StateXML>1</StateXML>
        </ScenarioActionStateChangerXML>

        <ScenarioActionStateChangerXML>
            <IdXML>pos:10030_sec:nitkatman1_type:hs2</IdXML>
            <StateXML>21</StateXML>
        </ScenarioActionStateChangerXML>
    
        <ScenarioActionStateChangerXML>
            <IdXML>pos:10100_sec:nitkatman1</IdXML>
            <StateXML>1</StateXML>
        </ScenarioActionStateChangerXML>
    </ScenarioEventXML>	
  
    <!-- frys pluss hast-->
    <ScenarioEventXML>
        <ScenarioTriggerTrackPosXML>		
            <IdXML>100</IdXML>							
            <SectionNameXML>nitkatman1</SectionNameXML>	
            <StartVertexXML>0,0,10390</StartVertexXML>
        </ScenarioTriggerTrackPosXML>				

        <ScenarioActionFreezeXML>						
            <MessageXML>freeze_nifty:niftyinfo1 imagefil=Lysbilde7.PNG oppg1=true oppg2=false oppg3=true oppg4=true
            </MessageXML>
        </ScenarioActionFreezeXML>
    </ScenarioEventXML>
  
    <!-- STOREHAMMER0 -->
    <ScenarioEventXML>
        <ScenarioActionStateChangerXML>
            <IdXML>a701</IdXML>
            <StateXML>22</StateXML>
        </ScenarioActionStateChangerXML>
    </ScenarioEventXML>

    <!-- STOREHAMMER1 -->
    <!-- signaler gjennom storeh-->
    <ScenarioEventXML>
        <ScenarioActionStateChangerXML>
            <IdXML>pos:595_sec:storehammer1_type:hs3</IdXML>
            <StateXML>22</StateXML>
        </ScenarioActionStateChangerXML>

        <ScenarioActionStateChangerXML>
            <IdXML>pos:595_sec:storehammer1_type:dv</IdXML>
            <StateXML>45</StateXML>
        </ScenarioActionStateChangerXML>

        <ScenarioActionStateChangerXML>
            <IdXML>pos:880_sec:storehammer1_type:hs3_x:0</IdXML>
            <StateXML>22</StateXML>
        </ScenarioActionStateChangerXML>

        <ScenarioActionStateChangerXML>
            <IdXML>pos:880_sec:storehammer1_type:dv_x:0</IdXML>
            <StateXML>45</StateXML>
        </ScenarioActionStateChangerXML>

        <ScenarioActionStateChangerXML>
            <IdXML>pos:1026_sec:storehammer1_type:dv_x:0</IdXML>
            <StateXML>45</StateXML>
        </ScenarioActionStateChangerXML>

        <ScenarioActionStateChangerXML>
            <IdXML>pos:1230_sec:storehammer1_type:hs3_x:0</IdXML>
            <StateXML>22</StateXML>
        </ScenarioActionStateChangerXML>
		
        <ScenarioActionStateChangerXML>
            <IdXML>pos:1230_sec:storehammer1_type:dv_x:0</IdXML>
            <StateXML>45</StateXML>
        </ScenarioActionStateChangerXML>
    </ScenarioEventXML>
  
  
    <!-- saktekjøring -->
    <!-- frys saktekj x 2-->
    <ScenarioEventXML>
        <ScenarioTriggerTrackPosXML>		
            <IdXML>100</IdXML>							
            <SectionNameXML>storehammer1</SectionNameXML>	
            <StartVertexXML>0,0,2490</StartVertexXML>
        </ScenarioTriggerTrackPosXML>				

        <ScenarioActionFreezeXML>						
            <MessageXML>freeze_nifty:niftyinfo1 imagefil=Lysbilde8.PNG oppg1=false oppg2=true oppg3=true oppg4=true
            </MessageXML>
        </ScenarioActionFreezeXML>
    </ScenarioEventXML>
  
    <ScenarioEventXML>
        <ScenarioTriggerTrackPosXML>		
            <IdXML>100</IdXML>							
            <SectionNameXML>revestua1</SectionNameXML>	
            <StartVertexXML>0,0,10</StartVertexXML>
        </ScenarioTriggerTrackPosXML>				

        <ScenarioActionFreezeXML>						
            <MessageXML>freeze_nifty:niftyinfo1 imagefil=Lysbilde9.PNG oppg1=false oppg2=false oppg3=true oppg4=true
            </MessageXML>
        </ScenarioActionFreezeXML>
    </ScenarioEventXML>
  
    <!-- frys ned hast pluss-->
    <ScenarioEventXML>
        <ScenarioTriggerTrackPosXML>		
            <IdXML>100</IdXML>							
            <SectionNameXML>revestua1</SectionNameXML>	
            <StartVertexXML>0,0,65</StartVertexXML>
        </ScenarioTriggerTrackPosXML>				

        <ScenarioActionFreezeXML>						
            <MessageXML>freeze_nifty:niftyinfo1 imagefil=Lysbilde10.PNG oppg1=true oppg2=true
            </MessageXML>
        </ScenarioActionFreezeXML>
    </ScenarioEventXML>
  
    <!-- varsel -->
    <NoSpeedTempDownXML>
        <SectionNameXML>storehammer1</SectionNameXML>
        <StartVertexXML>0.0, 0.0, 2500</StartVertexXML>
        <IdXML></IdXML>
        <OffsetVertexXML>-2.0, 0.0, 0.0</OffsetVertexXML>
        <DirectionXML>1</DirectionXML>
        <SignalFlashingXML>false</SignalFlashingXML>
        <NetIdXML>0</NetIdXML>
        <SpeedTextXML>8</SpeedTextXML>
    </NoSpeedTempDownXML>

    <BaliseScenarioBasedXML>		
        <SectionNameXML>storehammer1</SectionNameXML>    
        <StartVertexXML>0.0, 0.0, 2500</StartVertexXML>
        <OffsetVertexXML>0.0, 0.0, 0.0</OffsetVertexXML>
        <KodeXML>5, 8, 8</KodeXML>
    </BaliseScenarioBasedXML>

    <BaliseScenarioBasedXML>										
        <SectionNameXML>storehammer1</SectionNameXML>
        <StartVertexXML>0.0, 0.0, 2503</StartVertexXML>
        <OffsetVertexXML>0.0, 0.0, 0.0</OffsetVertexXML>
        <KodeXML>9, 4, 2</KodeXML>
    </BaliseScenarioBasedXML>
  
    <!-- låsing  --> 
    <NoSpeedTempUpXML>
        <SectionNameXML>storehammer1</SectionNameXML>
        <StartVertexXML>0.0, 0.0, 3250</StartVertexXML>
        <IdXML></IdXML>
        <OffsetVertexXML>2.0, 0.0, 0.0</OffsetVertexXML>
        <DirectionXML>-1</DirectionXML>
        <SignalFlashingXML>false</SignalFlashingXML>
        <NetIdXML>0</NetIdXML>
        <SpeedTextXML>9</SpeedTextXML>
    </NoSpeedTempUpXML>
  
    <BaliseScenarioBasedXML>
        <SectionNameXML>storehammer1</SectionNameXML>										
        <StartVertexXML>0.0, 0.0, 3250</StartVertexXML>
        <OffsetVertexXML>0.0, 0.0, 0.0</OffsetVertexXML>
        <KodeXML>5, 2, 8</KodeXML>
    </BaliseScenarioBasedXML>

    <BaliseScenarioBasedXML>	
        <SectionNameXML>storehammer1</SectionNameXML>									
        <StartVertexXML>0.0, 0.0, 3253</StartVertexXML>
        <OffsetVertexXML>0.0, 0.0, 0.0</OffsetVertexXML>
        <KodeXML>5, 5, 10</KodeXML>
    </BaliseScenarioBasedXML>

    <!-- låsing motsatt -->  
    <NoSpeedTempUpXML>
        <SectionNameXML>revestua1</SectionNameXML>
        <StartVertexXML>0.0, 0.0, 20</StartVertexXML>
        <IdXML></IdXML>
        <OffsetVertexXML>-2.0, 0.0, 0.0</OffsetVertexXML>
        <DirectionXML>1</DirectionXML>
        <SignalFlashingXML>false</SignalFlashingXML>
        <NetIdXML>0</NetIdXML>
        <SpeedTextXML>12</SpeedTextXML>
    </NoSpeedTempUpXML>
  
    <BaliseScenarioBasedXML>	
        <SectionNameXML>revestua1</SectionNameXML>									
        <StartVertexXML>0.0, 0.0, 20</StartVertexXML>
        <OffsetVertexXML>0.0, 0.0, 0.0</OffsetVertexXML>
        <KodeXML>5, 5, 10</KodeXML>
    </BaliseScenarioBasedXML>  

    <BaliseScenarioBasedXML>										
        <SectionNameXML>revestua1</SectionNameXML>
        <StartVertexXML>0.0, 0.0, 23</StartVertexXML>
        <OffsetVertexXML>0.0, 0.0, 0.0</OffsetVertexXML>
        <KodeXML>5, 2, 8</KodeXML>
    </BaliseScenarioBasedXML>
     
    <!-- varsel motsatt -->
    <NoSpeedTempDownXML>
        <SectionNameXML>revestua1</SectionNameXML>
        <StartVertexXML>0.0, 0.0, 750</StartVertexXML>
        <IdXML></IdXML>
        <OffsetVertexXML>2.0, 0.0, 0.0</OffsetVertexXML>
        <DirectionXML>-1</DirectionXML>
        <SignalFlashingXML>false</SignalFlashingXML>
        <NetIdXML>0</NetIdXML>
        <SpeedTextXML>8</SpeedTextXML>
    </NoSpeedTempDownXML>

    <BaliseScenarioBasedXML>										
        <SectionNameXML>revestua1</SectionNameXML>
        <StartVertexXML>0.0, 0.0, 750</StartVertexXML>
        <OffsetVertexXML>0.0, 0.0, 0.0</OffsetVertexXML>
        <KodeXML>9, 4, 2</KodeXML>
    </BaliseScenarioBasedXML>

    <BaliseScenarioBasedXML>										
        <SectionNameXML>revestua1</SectionNameXML>
        <StartVertexXML>0.0, 0.0, 753</StartVertexXML>
        <OffsetVertexXML>0.0, 0.0, 0.0</OffsetVertexXML>
        <KodeXML>5, 8, 8</KodeXML>
    </BaliseScenarioBasedXML>
  
  
  
    <!-- REVESTUA -->
    <!-- gjennomkjør -->
    <ScenarioEventXML>    
        <ScenarioActionStateChangerXML>
            <IdXML>pos:1890_sec:revestua1_type:hs3</IdXML>
            <StateXML>22</StateXML>
        </ScenarioActionStateChangerXML>
    
        <ScenarioActionStateChangerXML>
            <IdXML>pos:2525_sec:revestua1_type:hs3</IdXML>
            <StateXML>22</StateXML>
        </ScenarioActionStateChangerXML>
    
        <ScenarioActionStateChangerXML>
            <IdXML>pos:2429_sec:revestua1</IdXML>
            <StateXML>1</StateXML>
        </ScenarioActionStateChangerXML>
    </ScenarioEventXML>
  
    <!-- HAKAFJELL -->
    <!-- frys krengehast-->
    <ScenarioEventXML>
        <ScenarioTriggerTrackPosXML>		
            <IdXML>100</IdXML>							
            <SectionNameXML>hakafjell1</SectionNameXML>	
            <StartVertexXML>0,0,1320</StartVertexXML>
        </ScenarioTriggerTrackPosXML>
    
        <ScenarioActionFreezeXML>						
            <MessageXML>freeze_nifty:niftyinfo1 imagefil=Lysbilde11.PNG oppg1=false oppg2=true oppg3=false oppg4=true oppg5=true
            </MessageXML>
        </ScenarioActionFreezeXML>	  	 
    </ScenarioEventXML>
        
    <!-- signaler--> 
    <ScenarioEventXML>
        <!-- plo før hakafjell1-->
        <ScenarioActionStateChangerXML>
            <IdXML>pos:170_sec:hakafjell1</IdXML>
            <StateXML>1</StateXML>
        </ScenarioActionStateChangerXML>
    
        <ScenarioActionStateChangerXML>
            <IdXML>pos:1150_sec:hakafjell1_type:hs3</IdXML>
            <StateXML>22</StateXML>
        </ScenarioActionStateChangerXML>

        <ScenarioActionStateChangerXML>
            <IdXML>pos:1990_sec:hakafjell1_type:hs3</IdXML>
            <StateXML>22</StateXML>
        </ScenarioActionStateChangerXML>
    </ScenarioEventXML>
  
    <!-- LURBÅS -->
    <!-- frys avvikhast lys-->
    <ScenarioEventXML>
        <ScenarioTriggerTrackPosXML>		
            <IdXML>100</IdXML>							
            <SectionNameXML>GRS</SectionNameXML>	
            <StartVertexXML>0,0,1785</StartVertexXML>
        </ScenarioTriggerTrackPosXML>
    
        <ScenarioActionFreezeXML>						
            <MessageXML>freeze_nifty:niftyinfo1 imagefil=Lysbilde12.PNG oppg1=true oppg2=true oppg3=true
            </MessageXML>
        </ScenarioActionFreezeXML>	  	 
    </ScenarioEventXML>
  
    <!-- gjennomkjør -->
    <ScenarioEventXML>    
        <ScenarioActionStateChangerXML>
            <IdXML>pos:1801_sec:GRS_type:NoAvvikHastLys</IdXML>
            <StateXML>1</StateXML>
        </ScenarioActionStateChangerXML>
    
        <ScenarioActionStateChangerXML>
            <IdXML>pos:1801_sec:GRS_type:hs3</IdXML>
            <StateXML>21</StateXML>
        </ScenarioActionStateChangerXML>

        <ScenarioActionStateChangerXML>
            <IdXML>pos:2000_sec:GRS_type:dv</IdXML>
            <StateXML>45</StateXML>
        </ScenarioActionStateChangerXML>

        <ScenarioActionStateChangerXML>
            <IdXML>pos:2000_sec:GRS_type:sw</IdXML>
            <StateXML>1</StateXML>
        </ScenarioActionStateChangerXML>

        <ScenarioActionStateChangerXML>
            <IdXML>pos:2075_sec:GRS_type:dv</IdXML>
            <StateXML>45</StateXML>
        </ScenarioActionStateChangerXML>
    
        <ScenarioActionStateChangerXML>
            <IdXML>pos:2650_sec:GRS_type:dv_x:5</IdXML>
            <StateXML>45</StateXML>
        </ScenarioActionStateChangerXML>

        <ScenarioActionStateChangerXML>
            <IdXML>pos:2715_sec:GRS_type:dv_x:5</IdXML>
            <StateXML>45</StateXML>
        </ScenarioActionStateChangerXML>

        <ScenarioActionStateChangerXML>
            <IdXML>sv1</IdXML>
            <StateXML>1</StateXML>
        </ScenarioActionStateChangerXML>

        <ScenarioActionStateChangerXML>
            <IdXML>pos:2800_sec:GRS_type:sw</IdXML>
            <StateXML>1</StateXML>
        </ScenarioActionStateChangerXML>

        <ScenarioActionStateChangerXML>
            <IdXML>pos:2810_sec:GRS_type:hs3</IdXML>
            <StateXML>21</StateXML>
        </ScenarioActionStateChangerXML>
    </ScenarioEventXML>

    <!-- ny hast avvik SVG-->
    <ScenarioEventXML>
        <ScenarioActionBaliseErrorBitsXML>
            <IdXML>ba_svg1_lbs</IdXML>
            <MessageXML>6,0,10</MessageXML>	
        </ScenarioActionBaliseErrorBitsXML>	  
    </ScenarioEventXML>
  
    <!-- txp lbs -->
    <WorkerAc3dXML>
        <IdXML>txpLBS</IdXML>
        <SectionNameXML>GRS</SectionNameXML>
        <StartVertexXML>0, 0, 2420.0</StartVertexXML> 	
        <OffsetVertexXML>-4.5, 0.0, 0.0</OffsetVertexXML>
        <FileNameXML>TXPhilser.ac</FileNameXML>
        <DirectionXML>1</DirectionXML>						
    </WorkerAc3dXML>
  
    <!-- frys lurbås --> 
    <ScenarioEventXML>
        <ScenarioTriggerTrackPosXML>		
            <IdXML>100</IdXML>							
            <SectionNameXML>GRS</SectionNameXML>	
            <StartVertexXML>5,0,2400</StartVertexXML>
        </ScenarioTriggerTrackPosXML>
    
        <ScenarioActionFreezeXML>						
            <MessageXML>freeze_nifty:niftyinfo1 imagefil=Lysbilde13.PNG oppg1=true oppg2=true
            </MessageXML>
        </ScenarioActionFreezeXML>	  	 
    </ScenarioEventXML>
  
    <!-- frys saktekj uten atc --> 
    <ScenarioEventXML>
        <ScenarioTriggerTrackPosXML>		
            <IdXML>100</IdXML>							
            <SectionNameXML>GRS</SectionNameXML>	
            <StartVertexXML>0,0,3490</StartVertexXML>
        </ScenarioTriggerTrackPosXML>
    
        <ScenarioActionFreezeXML>						
            <MessageXML>freeze_nifty:niftyinfo1 imagefil=Lysbilde14.PNG oppg1=true oppg2=false oppg3=true
            </MessageXML>
        </ScenarioActionFreezeXML>	  	 
    </ScenarioEventXML>
  
    <!-- frys oppsummering --> 
    <ScenarioEventXML>
        <ScenarioTriggerTrackPosXML>		
            <IdXML>100</IdXML>							
            <SectionNameXML>GRS</SectionNameXML>	
            <StartVertexXML>0,0,4135</StartVertexXML>
        </ScenarioTriggerTrackPosXML>
    
        <ScenarioActionFreezeXML>						
            <MessageXML>freeze_nifty:niftyinfo1 imagefil=Lysbilde15.PNG
            </MessageXML>
            <AvsluttScenarioXML>true</AvsluttScenarioXML>
        </ScenarioActionFreezeXML>	  	 
    </ScenarioEventXML>
  
    <!-- varsel -->
    <NoSpeedTempDownXML>
        <SectionNameXML>GRS</SectionNameXML>
        <StartVertexXML>0.0, 0.0, 3500</StartVertexXML>
        <IdXML></IdXML>
        <OffsetVertexXML>-2.0, 0.0, 0.0</OffsetVertexXML>
        <DirectionXML>1</DirectionXML>
        <SignalFlashingXML>false</SignalFlashingXML>
        <NetIdXML>0</NetIdXML>
        <SpeedTextXML>4</SpeedTextXML>
    </NoSpeedTempDownXML>

  
    <!-- låsing  --> 
    <NoSpeedTempUpXML>
        <SectionNameXML>GRS</SectionNameXML>
        <StartVertexXML>0.0, 0.0, 4100</StartVertexXML>
        <IdXML></IdXML>
        <OffsetVertexXML>2.0, 0.0, 0.0</OffsetVertexXML>
        <DirectionXML>-1</DirectionXML>
        <SignalFlashingXML>false</SignalFlashingXML>
        <NetIdXML>0</NetIdXML>
        <SpeedTextXML>8</SpeedTextXML>
    </NoSpeedTempUpXML>
  

    <!-- låsing motsatt -->  
    <NoSpeedTempUpXML>
        <SectionNameXML>GRS</SectionNameXML>
        <StartVertexXML>0.0, 0.0, 4150</StartVertexXML>
        <IdXML></IdXML>
        <OffsetVertexXML>-2.0, 0.0, 0.0</OffsetVertexXML>
        <DirectionXML>1</DirectionXML>
        <SignalFlashingXML>false</SignalFlashingXML>
        <NetIdXML>0</NetIdXML>
        <SpeedTextXML>11</SpeedTextXML>
    </NoSpeedTempUpXML>


</ScenarioXML>

